picorun/__init__.py
picorun/errors.py
picorun/picorun.py
picorun-0.2.1.dist-info/LICENSE.txt
picorun-0.2.1.dist-info/METADATA
picorun-0.2.1.dist-info/WHEEL
picorun-0.2.1.dist-info/top_level.txt
picorun-0.2.1.dist-info/RECORD
