Metadata-Version: 2.1
Name: picorun
Version: 0.2.1
Summary: PicoFun runtime components
Author-email: Dave Hall <skwashd@gmail.com>
License: Copyright 2023 Dave Hall - https://proactiveops.io
License-File: LICENSE.txt
Requires-Dist: requests ==2.32.3
Provides-Extra: build
Requires-Dist: build ==1.2.1 ; extra == 'build'
Requires-Dist: twine ==5.1.1 ; extra == 'build'
Provides-Extra: dev
Requires-Dist: pytest ==8.3.2 ; extra == 'dev'
Requires-Dist: pytest-cov ==5.0.0 ; extra == 'dev'
Requires-Dist: pytest-mock ==3.14.0 ; extra == 'dev'
Requires-Dist: ruff ==0.6.3 ; extra == 'dev'
